rstyleslice/__init__.py
rstyleslice/_core.py
rstyleslice/docs/index.md
rstyleslice-1.4.5.dist-info/LICENSE
rstyleslice-1.4.5.dist-info/WHEEL
rstyleslice-1.4.5.dist-info/METADATA
rstyleslice-1.4.5.dist-info/RECORD
