Metadata-Version: 2.1
Name: rstyleslice
Version: 1.4.5
Summary: 一套符合直觉的索引和切片语法
Keywords: rstyleslice,slice
Author-email: "lcctoor.com" <lcctoor@outlook.com>
Requires-Python: >=3.7
Classifier: License :: OSI Approved :: Apache Software License
Project-URL: HomePage, https://lcctoor.github.io/lccpy/?package=rstyleslice
